[{
	"text":"物理分组",
		"children":[
			{"text":"海康NVR1",
				"id":"1",
				"state":"closed",
				"children":[
					{
						"text":"摄像头1",
						"id":"1"
					},{
						"text":"摄像头2",
						"id":"2"
					},{
						"text":"摄像头3",
						"id":"3"
					},{
						"text":"摄像头4",
						"id":"4"
					}
				]
			},{
				"text":"大华NVR1",
				"id":"2",
				"state":"closed",
				"children":[
					{
						"text":"摄像头1",
						"id":"1"
					},{
						"text":"摄像头2",
						"id":"2"
					},{
						"text":"摄像头3",
						"id":"3"
					},{
						"text":"摄像头4",
						"id":"4"
					}
				]
			},{
				"text":"海康NVR1",
				"id":"3",
				"state":"closed",
				"children":[
					{
						"text":"摄像头1",
						"id":"1"
					},{
						"text":"摄像头2",
						"id":"2"
					},{
						"text":"摄像头3",
						"id":"3"
					},{
						"text":"摄像头4",
						"id":"4"
					}
				]
			},{
				"text":"未分组",
				"state":"closed",
				"id":"4","children":[
					{
						"text":"摄像头1",
						"id":"1"
					},{
						"text":"摄像头2",
						"id":"2"
					},{
						"text":"摄像头3",
						"id":"3"
					},{
						"text":"摄像头4",
						"id":"4"
					}
				]
			}
			
		]
},{
	"text":"组织分组",
	"children":[
		{"text":"大门口",
			"id":"1",
			"state":"closed",
			"children":[
					{
						"text":"摄像头1",
						"id":"1"
					},{
						"text":"摄像头2",
						"id":"2"
					},{
						"text":"摄像头3",
						"id":"3"
					},{
						"text":"摄像头4",
						"id":"4"
					}
				]
		},{
			"text":"机房",
			"id":"2",
			"state":"closed",
			"children":[
					{
						"text":"摄像头1",
						"id":"1"
					},{
						"text":"摄像头2",
						"id":"2"
					},{
						"text":"摄像头3",
						"id":"3"
					},{
						"text":"摄像头4",
						"id":"4"
					}
				]
		},{
			"text":"车牌识别",
			"id":"3",
			"state":"closed",
			"children":[
					{
						"text":"摄像头1",
						"id":"1"
					},{
						"text":"摄像头2",
						"id":"2"
					},{
						"text":"摄像头3",
						"id":"3"
					},{
						"text":"摄像头4",
						"id":"4"
					}
				]
		},{
			"text":"人脸识别",
			"id":"4",
			"state":"closed",
			"children":[
					{
						"text":"摄像头1",
						"id":"1"
					},{
						"text":"摄像头2",
						"id":"2"
					},{
						"text":"摄像头3",
						"id":"3"
					},{
						"text":"摄像头4",
						"id":"4"
					}
				]
		},{
			"text":"未分组",
			"id":"4",
			"state":"closed",
			"children":[
					{
						"text":"摄像头1",
						"id":"1"
					},{
						"text":"摄像头2",
						"id":"2"
					},{
						"text":"摄像头3",
						"id":"3"
					},{
						"text":"摄像头4",
						"id":"4"
					}
				]
		}
		
	]
}]